data_wrangling/__init__.py
data_wrangling-0.0.2.dist-info/licenses/LICENSE
data_wrangling-0.0.2.dist-info/METADATA
data_wrangling-0.0.2.dist-info/WHEEL
data_wrangling-0.0.2.dist-info/top_level.txt
data_wrangling-0.0.2.dist-info/RECORD
