Metadata-Version: 2.4
Name: data-wrangling
Version: 0.0.2
Summary: A data wrangling package
Home-page: https://github.com/vanraak/data_wrangling
Author: Jeroen van Raak
Author-email: Jeroen van Raak <j.j.f.vanraak@uva.nl>
License: MIT
Project-URL: Homepage, https://github.com/vanraak/data_wrangling
Classifier: Programming Language :: Python :: 3
Classifier: License :: OSI Approved :: MIT License
Classifier: Operating System :: OS Independent
Requires-Python: >=3.6
License-File: LICENSE
Dynamic: author
Dynamic: home-page
Dynamic: license-file
Dynamic: requires-python
